FuzzyMath/__init__.py
FuzzyMath/class_factories.py
FuzzyMath/class_fuzzy_number.py
FuzzyMath/class_interval.py
FuzzyMath/class_membership_operations.py
FuzzyMath/class_memberships.py
FuzzyMath/class_precision.py
FuzzyMath/fuzzynumber_comparisons.py
FuzzyMath/py.typed
FuzzyMath-0.6.1.dist-info/LICENSE
FuzzyMath-0.6.1.dist-info/METADATA
FuzzyMath-0.6.1.dist-info/WHEEL
FuzzyMath-0.6.1.dist-info/top_level.txt
FuzzyMath-0.6.1.dist-info/RECORD
