Metadata-Version: 2.1
Name: FuzzyMath
Version: 0.6.1
Summary: Small lightweight library for Python that performs basic Interval and Fuzzy Arithmetic.
Author-email: Jan Caha <jan.caha@outlook.com>
License: MIT License
Project-URL: Documentation, https://jancaha.github.io/FuzzyMath
Keywords: fuzzy,fuzzy arithmetic,fuzzy math
Classifier: Development Status :: 3 - Alpha
Classifier: License :: OSI Approved :: MIT License
Classifier: Programming Language :: Python :: 3
Classifier: Programming Language :: Python :: 3.8
Classifier: Programming Language :: Python :: 3.9
Classifier: Programming Language :: Python :: 3.10
Classifier: Programming Language :: Python :: 3.11
Classifier: Programming Language :: Python :: 3.12
Classifier: Operating System :: POSIX :: Linux
Classifier: Operating System :: Microsoft :: Windows
Classifier: Operating System :: MacOS
Requires-Python: >=3.8
License-File: LICENSE
Requires-Dist: numpy
